{
  "version": "7",
  "dialect": "postgresql",
  "entries": [
    {
      "idx": 0,
      "version": "7",
      "when": 1749399200327,
      "tag": "0000_cloudy_mole_man",
      "breakpoints": true
    },
    {
      "idx": 1,
      "version": "7",
      "when": 1749457610534,
      "tag": "0001_aspiring_nico_minoru",
      "breakpoints": true
    },
    {
      "idx": 2,
      "version": "7",
      "when": 1749458713784,
      "tag": "0002_cultured_jack_flag",
      "breakpoints": true
    },
    {
      "idx": 3,
      "version": "7",
      "when": 1749459021407,
      "tag": "0003_exotic_night_thrasher",
      "breakpoints": true
    },
    {
      "idx": 4,
      "version": "7",
      "when": 1749532302242,
      "tag": "0004_text-search",
      "breakpoints": true
    },
    {
      "idx": 5,
      "version": "7",
      "when": 1749532450178,
      "tag": "0005_search-views",
      "breakpoints": true
    },
    {
      "idx": 6,
      "version": "7",
      "when": 1749532485588,
      "tag": "0006_materialized-view",
      "breakpoints": true
    }
  ]
}